<meta>
	<info author="OwlGamingPlus" type="script" description="Resources required for other systems to run."/>

	<!-- Fonts-->
	<file src="fonts/clbold.ttf"/>
	<file src="fonts/segoeuil.ttf"/>
	<file src="fonts/cartwheel.otf"/>
	<file src="fonts/Anton.ttf"/>
	<file src="fonts/BizNote.ttf"/>
	<file src="fonts/helveticastrong.ttf"/>
	<file src="fonts/digital.ttf"/>
	
	<!-- Images -->
	<file src="images/loading.jpg"/>
	<file src="images/window_body.png"/>
	<file src="images/OGLogo.png"/>

	<!-- Sounds -->
	<file src="sounds/inv_close.mp3"/>
	<file src="sounds/inv_open.mp3"/>
	<file src="sounds/inv_toggle.mp3"/>
	<file src="sounds/hb_on.mp3"/>
	<file src="sounds/hb_off.mp3"/>
	<file src="sounds/toggle.mp3"/>
</meta>
